super_csv/__init__.py
super_csv/admin.py
super_csv/apps.py
super_csv/common_settings.py
super_csv/csv_processor.py
super_csv/exceptions.py
super_csv/mixins.py
super_csv/models.py
super_csv/serializers.py
super_csv/signals.py
super_csv/tasks.py
super_csv/migrations/0001_initial.py
super_csv/migrations/0002_csvoperation_user.py
super_csv/migrations/0003_csvoperation_original_filename.py
super_csv/migrations/__init__.py
super_csv/templates/super_csv/base.html
super_csv-4.1.0.dist-info/licenses/LICENSE.txt
super_csv-4.1.0.dist-info/METADATA
super_csv-4.1.0.dist-info/WHEEL
super_csv-4.1.0.dist-info/entry_points.txt
super_csv-4.1.0.dist-info/top_level.txt
super_csv-4.1.0.dist-info/RECORD
