Metadata-Version: 2.4
Name: super-csv
Version: 4.1.0
Summary: CSV Processor
Home-page: https://github.com/openedx/super-csv
Author: edX
Author-email: oscm@edx.org
License: Apache 2.0
Keywords: Django edx
Classifier: Development Status :: 3 - Alpha
Classifier: Framework :: Django
Classifier: Framework :: Django :: 4.2
Classifier: Framework :: Django :: 5.2
Classifier: Intended Audience :: Developers
Classifier: License :: OSI Approved :: Apache Software License
Classifier: Natural Language :: English
Classifier: Programming Language :: Python :: 3
Classifier: Programming Language :: Python :: 3.11
Classifier: Programming Language :: Python :: 3.12
License-File: LICENSE.txt
Requires-Dist: edx-celeryutils
Requires-Dist: simplejson
Requires-Dist: Django
Requires-Dist: django-crum
Requires-Dist: django-model-utils
Requires-Dist: edx-django-utils>=3.12.0
Requires-Dist: djangorestframework
Dynamic: author
Dynamic: author-email
Dynamic: classifier
Dynamic: description
Dynamic: description-content-type
Dynamic: home-page
Dynamic: keywords
Dynamic: license
Dynamic: license-file
Dynamic: requires-dist
Dynamic: summary
